superlaser/__init__.py
superlaser/inference.py
superlaser/runpod/__init__.py
superlaser/runpod/data.py
superlaser/runpod/models.py
superlaser/runpod/request.py
superlaser/utils/__init__.py
superlaser/utils/errata.py
superlaser/utils/hf_utils.py
superlaser-0.0.6.dist-info/LICENSE
superlaser-0.0.6.dist-info/METADATA
superlaser-0.0.6.dist-info/WHEEL
superlaser-0.0.6.dist-info/top_level.txt
superlaser-0.0.6.dist-info/RECORD
