Metadata-Version: 2.1
Name: superlaser
Version: 0.0.6
Summary: An MLOps library for LLM deployment w/ the vLLM engine on RunPod's infra.
Home-page: UNKNOWN
Author: InquestGeronimo
Author-email: rcostanl@gmail.com
License: Apache-2.0 license
Keywords: inference,server,LLM,NLP,MLOps,deployment,vllm,runpod,cicd
Platform: UNKNOWN
Classifier: Development Status :: 1 - Planning
Classifier: Intended Audience :: Developers
Classifier: Programming Language :: Python :: 3
Classifier: Operating System :: Unix
License-File: LICENSE
Requires-Dist: huggingface-hub >=0.21.1
Requires-Dist: openai >=1.13.3
